tgbox/__init__.py
tgbox/crypto.py
tgbox/defaults.py
tgbox/errors.py
tgbox/fastelethon.py
tgbox/keys.py
tgbox/tools.py
tgbox/version.py
tgbox/api/__init__.py
tgbox/api/abstract.py
tgbox/api/db.py
tgbox/api/local.py
tgbox/api/remote.py
tgbox/api/sync.py
tgbox/api/utils.py
tgbox/other/tgbox_logo.png
tgbox/other/words.txt
tgbox-1.7.dist-info/licenses/LICENSE
tgbox-1.7.dist-info/METADATA
tgbox-1.7.dist-info/WHEEL
tgbox-1.7.dist-info/top_level.txt
tgbox-1.7.dist-info/RECORD
