Metadata-Version: 2.4
Name: tgbox
Version: 1.7
Summary: Encrypted cloud storage Protocol based on a Telegram API
Home-page: https://github.com/NonProjects/tgbox
Download-URL: https://github.com/NonProjects/tgbox/archive/refs/tags/v1.7.tar.gz
Author: NonProjects
Author-email: thenonproton@pm.me
License: LGPL-2.1
Keywords: Telegram,Cloud-Storage,Cloud,API,Asyncio,Non-official
Classifier: Development Status :: 5 - Production/Stable
Classifier: Intended Audience :: Developers
Classifier: Topic :: Security :: Cryptography
Classifier: Topic :: Software Development :: Libraries
Classifier: Programming Language :: Python :: 3.9
License-File: LICENSE
Requires-Dist: aiosqlite==0.21.0
Requires-Dist: telethon==1.41.2
Requires-Dist: ecdsa==0.19.0
Requires-Dist: filetype==1.2.0
Requires-Dist: pysocks==1.7.1
Provides-Extra: doc
Requires-Dist: sphinx-book-theme==1.1.4; extra == "doc"
Requires-Dist: sphinx-togglebutton==0.3.2; extra == "doc"
Provides-Extra: fast
Requires-Dist: cryptography<47.0.0; extra == "fast"
Requires-Dist: cryptg==0.5.2; extra == "fast"
Requires-Dist: uvloop==0.22.1; extra == "fast"
Dynamic: author
Dynamic: author-email
Dynamic: classifier
Dynamic: description
Dynamic: description-content-type
Dynamic: download-url
Dynamic: home-page
Dynamic: keywords
Dynamic: license
Dynamic: license-file
Dynamic: provides-extra
Dynamic: requires-dist
Dynamic: summary
